img_utils/__init__.py
img_utils/colors/__init__.py
img_utils/colors/color.py
img_utils/files/__init__.py
img_utils/files/file.py
img_utils/images/__init__.py
img_utils/images/geometry.py
img_utils/images/image.py
img_utils-0.0.13.dist-info/DESCRIPTION.rst
img_utils-0.0.13.dist-info/METADATA
img_utils-0.0.13.dist-info/RECORD
img_utils-0.0.13.dist-info/WHEEL
img_utils-0.0.13.dist-info/metadata.json
img_utils-0.0.13.dist-info/top_level.txt
img_utils-0.0.13.dist-info/zip-safe
