Metadata-Version: 2.0
Name: img-utils
Version: 0.0.13
Summary: Convenient functions that help to process images
Home-page: https://github.com/DewMaple/img_utils
Author: dew.maple
Author-email: dew.maple@gmail.com
License: MIT
Project-URL: Bug Reports, https://github.com/DewMaple/img_utils/issues
Project-URL: Source, https://github.com/DewMaple/img_utils
Keywords: computer vision,image processing,opencv,numpy
Platform: UNKNOWN
Classifier: Programming Language :: Python :: 3.6
